Metadata-Version: 2.1
Name: codecheck
Version: 1.2.0
Summary: A tool for quickly running checks on a set of source code files in a project
Home-page: https://github.com/yugabyte/codecheck
Author: Mikhail Bautin
Author-email: mbautin@users.noreply.github.com
License: UNKNOWN
Platform: UNKNOWN
Provides-Extra: dev
License-File: LICENSE
